wedo2
