Metadata-Version: 1.1
Name: wedo2
Version: 1.1.1
Summary: Python SDK for LEGO WeDo 2.0
Home-page: https://github.com/jannopet/LEGO-WeDo-2.0-Python-SDK
Author: Janno Peterson
Author-email: janno.peterson@gmail.com
License: MIT
Keywords: SDK lego education
Platform: UNKNOWN
Classifier: Development Status :: 4 - Beta
Classifier: Environment :: MacOS X
Classifier: Environment :: Win32 (MS Windows)
Classifier: Intended Audience :: Developers
Classifier: Intended Audience :: Education
Classifier: Intended Audience :: End Users/Desktop
Classifier: License :: OSI Approved :: MIT License
Classifier: Natural Language :: English
Classifier: Programming Language :: Python
Classifier: Programming Language :: Python :: 3 :: Only
Classifier: Programming Language :: Python :: 3.4
Classifier: Programming Language :: Python :: 3.5
Classifier: Programming Language :: Python :: 3.6
Classifier: Topic :: Education
Classifier: Topic :: Software Development
